CHANGES.txt
CONTRIBUTORS.txt
README.txt
bootstrap.py
buildout.cfg
setup.py
collective/__init__.py
collective.recipe.filestorage.egg-info/PKG-INFO
collective.recipe.filestorage.egg-info/SOURCES.txt
collective.recipe.filestorage.egg-info/dependency_links.txt
collective.recipe.filestorage.egg-info/entry_points.txt
collective.recipe.filestorage.egg-info/namespace_packages.txt
collective.recipe.filestorage.egg-info/not-zip-safe
collective.recipe.filestorage.egg-info/requires.txt
collective.recipe.filestorage.egg-info/top_level.txt
collective/recipe/__init__.py
collective/recipe/filestorage/README.txt
collective/recipe/filestorage/TODO.txt
collective/recipe/filestorage/__init__.py
collective/recipe/filestorage/tests/__init__.py
collective/recipe/filestorage/tests/test_docs.py
collective/recipe/filestorage/tests/zope2/bin/mkzopeinstance.py
collective/recipe/filestorage/tests/zope2/lib/python/ZEO/__init__.py
collective/recipe/filestorage/tests/zope2/lib/python/ZEO/mkzeoinst.py