Metadata-Version: 1.0
Name: collective.recipe.filestorage
Version: 0.6
Summary: This recipe aids the creation and management of multiple Zope 2 filestorages.
Home-page: http://svn.plone.org/svn/collective/buildout/collective.recipe.filestorage/trunk
Author: David Glick
Author-email: davidglick@onenw.org
License: ZPL
Keywords: buildout zope zeo zodb mountpoint filestorage
Platform: UNKNOWN
Classifier: Framework :: Buildout
Classifier: Framework :: Zope2
Classifier: Intended Audience :: Developers
Classifier: Topic :: Software Development :: Build Tools
Classifier: Topic :: Software Development :: Libraries :: Python Modules
Classifier: License :: OSI Approved :: Zope Public License
